{
  "nodes": [
    {
      "final": false,
      "entry": false,
      "pos": "access-nsieve.js:30:1",
      "id": 52,
      "label": "[access-nsieve]sieve"
    },
    {
      "final": true,
      "entry": false,
      "pos": "access-nsieve.js:15:1",
      "id": 53,
      "label": "[access-nsieve]nsieve"
    },
    {
      "final": false,
      "entry": false,
      "pos": "toplevel:1:1",
      "id": 54,
      "label": "[access-nsieve]"
    }
  ],
  "links": [
    {
      "source": 52,
      "target": 53,
      "label": "[access-nsieve]sieve -> [access-nsieve]nsieve"
    },
    {
      "source": 54,
      "target": 52,
      "label": "[access-nsieve] -> [access-nsieve]sieve"
    }
  ]
}