{"links": [{"source": 0, "target": 1}, {"source": 1, "target": 2}, {"source": 1, "target": 3}, {"source": 3, "target": 4}, {"source": 4, "target": 5}, {"source": 4, "target": 7}, {"source": 5, "target": 6}, {"source": 6, "target": 6}, {"source": 7, "target": 6}], "graph": {"edge_default": {}, "node_default": {}}, "directed": true, "nodes": [{"id": 0, "label": "ENTRY", "entry": true}, {"id": 1, "label": "main", "final": true}, {"id": 2, "label": "InfoTbl", "final": true}, {"id": 3, "label": "QChiSq"}, {"id": 4, "label": "QGamma"}, {"id": 5, "label": "gser", "final": true}, {"id": 6, "label": "LGamma", "final": true}, {"id": 7, "label": "gcf"}], "multigraph": false}