{
  "nodes": [
    {
      "id": 1,
      "label": "[crypto-aes.js]encodeBase64",
      "pos": "crypto-aes.js:292:1"
    },
    {
      "id": 2,
      "label": "[crypto-aes.js]encodeUTF8",
      "pos": "crypto-aes.js:343:1"
    },
    {
      "id": 3,
      "label": "[crypto-aes.js]decodeBase64",
      "pos": "crypto-aes.js:320:1"
    },
    {
      "id": 4,
      "label": "[crypto-aes.js]decodeUTF8",
      "pos": "crypto-aes.js:359:1"
    },
    {
      "id": 5,
      "label": "[crypto-aes.js]KeyExpansion",
      "pos": "crypto-aes.js:83:1"
    },
    {
      "id": 6,
      "label": "[crypto-aes.js]RotWord",
      "pos": "crypto-aes.js:116:1"
    },
    {
      "id": 7,
      "label": "[crypto-aes.js]SubWord",
      "pos": "crypto-aes.js:111:1"
    },
    {
      "id": 8,
      "label": "[crypto-aes.js]Cipher",
      "pos": "crypto-aes.js:13:1"
    },
    {
      "id": 9,
      "label": "[crypto-aes.js]AddRoundKey",
      "pos": "crypto-aes.js:75:1"
    },
    {
      "id": 10,
      "label": "[crypto-aes.js]SubBytes",
      "pos": "crypto-aes.js:39:1"
    },
    {
      "id": 11,
      "label": "[crypto-aes.js]ShiftRows",
      "pos": "crypto-aes.js:47:1"
    },
    {
      "id": 12,
      "label": "[crypto-aes.js]MixColumns",
      "pos": "crypto-aes.js:57:1"
    },
    {
      "id": 13,
      "label": "[crypto-aes.js]AESDecryptCtr",
      "pos": "crypto-aes.js:230:1"
    },
    {
      "id": 14,
      "label": "[crypto-aes.js]unescCtrlChars",
      "pos": "crypto-aes.js:282:1"
    },
    {
      "id": 15,
      "label": "[toplevel]",
      "pos": "toplevel:1:1"
    },
    {
      "id": 16,
      "label": "[crypto-aes.js]AESEncryptCtr",
      "pos": "crypto-aes.js:164:1"
    },
    {
      "id": 17,
      "label": "[crypto-aes.js]escCtrlChars",
      "pos": "crypto-aes.js:278:1"
    }
  ],
  "links": [
    {
      "target": 2,
      "source": 1,
      "label": "[crypto-aes.js]encodeBase64 -> [crypto-aes.js]encodeUTF8"
    },
    {
      "target": 4,
      "source": 3,
      "label": "[crypto-aes.js]decodeBase64 -> [crypto-aes.js]decodeUTF8"
    },
    {
      "target": 6,
      "source": 5,
      "label": "[crypto-aes.js]KeyExpansion -> [crypto-aes.js]RotWord"
    },
    {
      "target": 7,
      "source": 5,
      "label": "[crypto-aes.js]KeyExpansion -> [crypto-aes.js]SubWord"
    },
    {
      "target": 9,
      "source": 8,
      "label": "[crypto-aes.js]Cipher -> [crypto-aes.js]AddRoundKey"
    },
    {
      "target": 10,
      "source": 8,
      "label": "[crypto-aes.js]Cipher -> [crypto-aes.js]SubBytes"
    },
    {
      "target": 11,
      "source": 8,
      "label": "[crypto-aes.js]Cipher -> [crypto-aes.js]ShiftRows"
    },
    {
      "target": 12,
      "source": 8,
      "label": "[crypto-aes.js]Cipher -> [crypto-aes.js]MixColumns"
    },
    {
      "target": 5,
      "source": 13,
      "label": "[crypto-aes.js]AESDecryptCtr -> [crypto-aes.js]KeyExpansion"
    },
    {
      "target": 8,
      "source": 13,
      "label": "[crypto-aes.js]AESDecryptCtr -> [crypto-aes.js]Cipher"
    },
    {
      "target": 14,
      "source": 13,
      "label": "[crypto-aes.js]AESDecryptCtr -> [crypto-aes.js]unescCtrlChars"
    },
    {
      "target": 16,
      "source": 15,
      "label": "[toplevel] -> [crypto-aes.js]AESEncryptCtr"
    },
    {
      "target": 13,
      "source": 15,
      "label": "[toplevel] -> [crypto-aes.js]AESDecryptCtr"
    },
    {
      "target": 5,
      "source": 16,
      "label": "[crypto-aes.js]AESEncryptCtr -> [crypto-aes.js]KeyExpansion"
    },
    {
      "target": 8,
      "source": 16,
      "label": "[crypto-aes.js]AESEncryptCtr -> [crypto-aes.js]Cipher"
    },
    {
      "target": 17,
      "source": 16,
      "label": "[crypto-aes.js]AESEncryptCtr -> [crypto-aes.js]escCtrlChars"
    }
  ]
}